{"match_id":"b332a9a1-6cdf-4d5d-9289-270135ff1af5.nakama-0","map":"AmbroseValley","events":[{"t":0.0,"x":0.667039,"y":0.232596,"type":"position","is_bot":false,"player_id":"23f4ebd6-389f-4659-a135-f80b419475cc"},{"t":0.02,"x":0.670394,"y":0.242339,"type":"position","is_bot":false,"player_id":"23f4ebd6-389f-4659-a135-f80b419475cc"},{"t":0.025,"x":0.667784,"y":0.270782,"type":"position","is_bot":false,"player_id":"23f4ebd6-389f-4659-a135-f80b419475cc"},{"t":0.03,"x":0.646554,"y":0.299572,"type":"position","is_bot":false,"player_id":"23f4ebd6-389f-4659-a135-f80b419475cc"},{"t":0.035,"x":0.622518,"y":0.326342,"type":"position","is_bot":false,"player_id":"23f4ebd6-389f-4659-a135-f80b419475cc"},{"t":0.04,"x":0.61111,"y":0.339378,"type":"position","is_bot":false,"player_id":"23f4ebd6-389f-4659-a135-f80b419475cc"},{"t":0.045,"x":0.602095,"y":0.368543,"type":"position","is_bot":false,"player_id":"23f4ebd6-389f-4659-a135-f80b419475cc"},{"t":0.05,"x":0.592675,"y":0.375756,"type":"position","is_bot":false,"player_id":"23f4ebd6-389f-4659-a135-f80b419475cc"},{"t":0.051,"x":0.59193,"y":0.373728,"type":"kill","is_bot":false,"player_id":"23f4ebd6-389f-4659-a135-f80b419475cc"},{"t":0.055,"x":0.590063,"y":0.384461,"type":"position","is_bot":false,"player_id":"23f4ebd6-389f-4659-a135-f80b419475cc"},{"t":0.056,"x":0.589971,"y":0.383004,"type":"loot","is_bot":false,"player_id":"23f4ebd6-389f-4659-a135-f80b419475cc"},{"t":0.058,"x":0.589971,"y":0.383004,"type":"loot","is_bot":false,"player_id":"23f4ebd6-389f-4659-a135-f80b419475cc"},{"t":0.06,"x":0.588125,"y":0.388647,"type":"position","is_bot":false,"player_id":"23f4ebd6-389f-4659-a135-f80b419475cc"},{"t":0.065,"x":0.56933,"y":0.398318,"type":"position","is_bot":false,"player_id":"23f4ebd6-389f-4659-a135-f80b419475cc"},{"t":0.075,"x":0.577243,"y":0.391411,"type":"position","is_bot":false,"player_id":"23f4ebd6-389f-4659-a135-f80b419475cc"},{"t":0.078,"x":0.577022,"y":0.391195,"type":"loot","is_bot":false,"player_id":"23f4ebd6-389f-4659-a135-f80b419475cc"},{"t":0.08,"x":0.576627,"y":0.385761,"type":"position","is_bot":false,"player_id":"23f4ebd6-389f-4659-a135-f80b419475cc"},{"t":0.084,"x":0.584329,"y":0.402259,"type":"loot","is_bot":false,"player_id":"23f4ebd6-389f-4659-a135-f80b419475cc"},{"t":0.085,"x":0.584329,"y":0.402259,"type":"position","is_bot":false,"player_id":"23f4ebd6-389f-4659-a135-f80b419475cc"},{"t":0.086,"x":0.584329,"y":0.402259,"type":"loot","is_bot":false,"player_id":"23f4ebd6-389f-4659-a135-f80b419475cc"},{"t":0.09,"x":0.584127,"y":0.425066,"type":"position","is_bot":false,"player_id":"23f4ebd6-389f-4659-a135-f80b419475cc"},{"t":0.095,"x":0.56112,"y":0.449166,"type":"position","is_bot":false,"player_id":"23f4ebd6-389f-4659-a135-f80b419475cc"},{"t":0.1,"x":0.54422,"y":0.468968,"type":"position","is_bot":false,"player_id":"23f4ebd6-389f-4659-a135-f80b419475cc"},{"t":0.105,"x":0.545398,"y":0.466555,"type":"position","is_bot":false,"player_id":"23f4ebd6-389f-4659-a135-f80b419475cc"},{"t":0.11,"x":0.543823,"y":0.472736,"type":"position","is_bot":false,"player_id":"23f4ebd6-389f-4659-a135-f80b419475cc"},{"t":0.135,"x":0.538376,"y":0.476828,"type":"position","is_bot":false,"player_id":"23f4ebd6-389f-4659-a135-f80b419475cc"},{"t":0.14,"x":0.537696,"y":0.510093,"type":"position","is_bot":false,"player_id":"23f4ebd6-389f-4659-a135-f80b419475cc"},{"t":0.146,"x":0.539033,"y":0.513457,"type":"position","is_bot":false,"player_id":"23f4ebd6-389f-4659-a135-f80b419475cc"},{"t":0.151,"x":0.545759,"y":0.521607,"type":"position","is_bot":false,"player_id":"23f4ebd6-389f-4659-a135-f80b419475cc"},{"t":0.156,"x":0.550024,"y":0.525512,"type":"position","is_bot":false,"player_id":"23f4ebd6-389f-4659-a135-f80b419475cc"},{"t":0.161,"x":0.550558,"y":0.520698,"type":"position","is_bot":false,"player_id":"23f4ebd6-389f-4659-a135-f80b419475cc"},{"t":0.165,"x":0.553645,"y":0.509108,"type":"kill","is_bot":false,"player_id":"23f4ebd6-389f-4659-a135-f80b419475cc"},{"t":0.166,"x":0.554212,"y":0.505985,"type":"position","is_bot":false,"player_id":"23f4ebd6-389f-4659-a135-f80b419475cc"},{"t":0.171,"x":0.55501,"y":0.507922,"type":"position","is_bot":false,"player_id":"23f4ebd6-389f-4659-a135-f80b419475cc"},{"t":0.175,"x":0.553197,"y":0.504741,"type":"kill","is_bot":false,"player_id":"23f4ebd6-389f-4659-a135-f80b419475cc"},{"t":0.176,"x":0.551952,"y":0.505201,"type":"position","is_bot":false,"player_id":"23f4ebd6-389f-4659-a135-f80b419475cc"},{"t":0.181,"x":0.533406,"y":0.507561,"type":"position","is_bot":false,"player_id":"23f4ebd6-389f-4659-a135-f80b419475cc"},{"t":0.186,"x":0.502615,"y":0.500889,"type":"position","is_bot":false,"player_id":"23f4ebd6-389f-4659-a135-f80b419475cc"},{"t":0.191,"x":0.494583,"y":0.49482,"type":"position","is_bot":false,"player_id":"23f4ebd6-389f-4659-a135-f80b419475cc"},{"t":0.204,"x":0.494583,"y":0.49482,"type":"kill","is_bot":false,"player_id":"23f4ebd6-389f-4659-a135-f80b419475cc"},{"t":0.226,"x":0.485943,"y":0.483695,"type":"position","is_bot":false,"player_id":"23f4ebd6-389f-4659-a135-f80b419475cc"},{"t":0.231,"x":0.461671,"y":0.470332,"type":"position","is_bot":false,"player_id":"23f4ebd6-389f-4659-a135-f80b419475cc"},{"t":0.236,"x":0.452113,"y":0.477419,"type":"position","is_bot":false,"player_id":"23f4ebd6-389f-4659-a135-f80b419475cc"},{"t":0.241,"x":0.45632,"y":0.478363,"type":"position","is_bot":false,"player_id":"23f4ebd6-389f-4659-a135-f80b419475cc"},{"t":0.246,"x":0.455521,"y":0.475003,"type":"position","is_bot":false,"player_id":"23f4ebd6-389f-4659-a135-f80b419475cc"},{"t":0.256,"x":0.455651,"y":0.479034,"type":"position","is_bot":false,"player_id":"23f4ebd6-389f-4659-a135-f80b419475cc"},{"t":0.261,"x":0.453302,"y":0.477962,"type":"position","is_bot":false,"player_id":"23f4ebd6-389f-4659-a135-f80b419475cc"},{"t":0.266,"x":0.460176,"y":0.480721,"type":"position","is_bot":false,"player_id":"23f4ebd6-389f-4659-a135-f80b419475cc"},{"t":0.271,"x":0.455628,"y":0.483977,"type":"loot","is_bot":false,"player_id":"23f4ebd6-389f-4659-a135-f80b419475cc"},{"t":0.276,"x":0.448327,"y":0.500524,"type":"position","is_bot":false,"player_id":"23f4ebd6-389f-4659-a135-f80b419475cc"},{"t":0.28,"x":0.445708,"y":0.506715,"type":"loot","is_bot":false,"player_id":"23f4ebd6-389f-4659-a135-f80b419475cc"},{"t":0.28,"x":0.445363,"y":0.506561,"type":"death","is_bot":false,"player_id":"23f4ebd6-389f-4659-a135-f80b419475cc"},{"t":0.281,"x":0.445363,"y":0.506561,"type":"position","is_bot":false,"player_id":"23f4ebd6-389f-4659-a135-f80b419475cc"}]}